{
"type": "FeatureCollection",
"name": "chapel hill points geoJSON",
"crs": { "type": "name", "properties": { "name": "urn:ogc:def:crs:OGC:1.3:CRS84" } },
"features": [
{ "type": "Feature", "properties": { "id": 1, "key points": "football stadium", "notes": null }, "geometry": { "type": "Point", "coordinates": [ -79.04786763276158, 35.906990469860318 ] } },
{ "type": "Feature", "properties": { "id": 2, "key points": "bell tower", "notes": null }, "geometry": { "type": "Point", "coordinates": [ -79.049236151067802, 35.908613010792038 ] } },
{ "type": "Feature", "properties": { "id": 3, "key points": "morehead sundial", "notes": null }, "geometry": { "type": "Point", "coordinates": [ -79.05095738093911, 35.914458194618781 ] } },
{ "type": "Feature", "properties": { "id": 4, "key points": "morehead planetarium", "notes": null }, "geometry": { "type": "Point", "coordinates": [ -79.050836160489922, 35.913861642938429 ] } },
{ "type": "Feature", "properties": { "id": 5, "key points": "old well", "notes": null }, "geometry": { "type": "Point", "coordinates": [ -79.051242823424985, 35.912060298053575 ] } }
]
}
